README.rst
setup.py
teambot/__init__.py
teambot/bot.py
teambot/console.py
teambot/handler.py
teambot.egg-info/PKG-INFO
teambot.egg-info/SOURCES.txt
teambot.egg-info/dependency_links.txt
teambot.egg-info/entry_points.txt
teambot.egg-info/requires.txt
teambot.egg-info/top_level.txt