Metadata-Version: 1.1
Name: teambot
Version: 0.2.0
Summary: teambot
Home-page: https://git.tilde.team/meta/teambot
Author: Robert Miles
Author-email: khuxkm@tilde.team
License: MIT
Keywords: irc,bot
Platform: UNKNOWN
Classifier: Programming Language :: Python
Classifier: Programming Language :: Python :: 3.3
